{"success":1,"results":{"start_date":1672012800,"end_date":1715472000,"weeks":[],"rollups":[{"date":1672012800,"recommendations_up":50,"recommendations_down":42},{"date":1672617600,"recommendations_up":21,"recommendations_down":16},{"date":1673222400,"recommendations_up":9,"recommendations_down":9},{"date":1673827200,"recommendations_up":4,"recommendations_down":8},{"date":1674432000,"recommendations_up":8,"recommendations_down":8},{"date":1675036800,"recommendations_up":2,"recommendations_down":7},{"date":1675641600,"recommendations_up":2,"recommendations_down":5},{"date":1676246400,"recommendations_up":4,"recommendations_down":3},{"date":1676851200,"recommendations_up":0,"recommendations_down":1},{"date":1677456000,"recommendations_up":2,"recommendations_down":2},{"date":1678060800,"recommendations_up":3,"recommendations_down":0},{"date":1678665600,"recommendations_up":3,"recommendations_down":1},{"date":1679270400,"recommendations_up":3,"recommendations_down":1},{"date":1679875200,"recommendations_up":1,"recommendations_down":7},{"date":1680480000,"recommendations_up":1,"recommendations_down":0},{"date":1681084800,"recommendations_up":2,"recommendations_down":2},{"date":1681689600,"recommendations_up":0,"recommendations_down":4},{"date":1682294400,"recommendations_up":2,"recommendations_down":1},{"date":1682899200,"recommendations_up":4,"recommendations_down":5},{"date":1683504000,"recommendations_up":2,"recommendations_down":4},{"date":1684108800,"recommendations_up":0,"recommendations_down":1},{"date":1684713600,"recommendations_up":3,"recommendations_down":3},{"date":1685318400,"recommendations_up":1,"recommendations_down":5},{"date":1686528000,"recommendations_up":0,"recommendations_down":3},{"date":1687132800,"recommendations_up":2,"recommendations_down":2},{"date":1687737600,"recommendations_up":1,"recommendations_down":1},{"date":1688342400,"recommendations_up":2,"recommendations_down":3},{"date":1688947200,"recommendations_up":0,"recommendations_down":2},{"date":1690156800,"recommendations_up":1,"recommendations_down":2},{"date":1690761600,"recommendations_up":1,"recommendations_down":1},{"date":1691366400,"recommendations_up":1,"recommendations_down":0},{"date":1691971200,"recommendations_up":2,"recommendations_down":1},{"date":1692576000,"recommendations_up":1,"recommendations_down":2},{"date":1693180800,"recommendations_up":1,"recommendations_down":3},{"date":1693785600,"recommendations_up":6,"recommendations_down":4},{"date":1694390400,"recommendations_up":2,"recommendations_down":3},{"date":1694995200,"recommendations_up":0,"recommendations_down":1},{"date":1696204800,"recommendations_up":0,"recommendations_down":1},{"date":1696809600,"recommendations_up":0,"recommendations_down":2},{"date":1697414400,"recommendations_up":0,"recommendations_down":1},{"date":1698019200,"recommendations_up":1,"recommendations_down":0},{"date":1699833600,"recommendations_up":14,"recommendations_down":1},{"date":1700438400,"recommendations_up":4,"recommendations_down":0},{"date":1701043200,"recommendations_up":0,"recommendations_down":2},{"date":1701648000,"recommendations_up":1,"recommendations_down":0},{"date":1702252800,"recommendations_up":2,"recommendations_down":0},{"date":1702857600,"recommendations_up":1,"recommendations_down":2},{"date":1704067200,"recommendations_up":1,"recommendations_down":0},{"date":1704672000,"recommendations_up":3,"recommendations_down":1},{"date":1705276800,"recommendations_up":3,"recommendations_down":1},{"date":1705881600,"recommendations_up":2,"recommendations_down":1},{"date":1706486400,"recommendations_up":0,"recommendations_down":2},{"date":1707091200,"recommendations_up":1,"recommendations_down":1},{"date":1707696000,"recommendations_up":1,"recommendations_down":1},{"date":1708300800,"recommendations_up":1,"recommendations_down":1},{"date":1709510400,"recommendations_up":1,"recommendations_down":3},{"date":1710115200,"recommendations_up":1,"recommendations_down":0},{"date":1710720000,"recommendations_up":1,"recommendations_down":0},{"date":1711324800,"recommendations_up":4,"recommendations_down":1},{"date":1711929600,"recommendations_up":1,"recommendations_down":1},{"date":1712534400,"recommendations_up":1,"recommendations_down":2},{"date":1713139200,"recommendations_up":0,"recommendations_down":1},{"date":1713744000,"recommendations_up":0,"recommendations_down":1},{"date":1714348800,"recommendations_up":0,"recommendations_down":1},{"date":1714953600,"recommendations_up":1,"recommendations_down":2}],"rollup_type":"week","recent":[{"date":1712966400,"recommendations_up":0,"recommendations_down":0},{"date":1713052800,"recommendations_up":1,"recommendations_down":0},{"date":1713139200,"recommendations_up":0,"recommendations_down":0},{"date":1713225600,"recommendations_up":0,"recommendations_down":0},{"date":1713312000,"recommendations_up":0,"recommendations_down":0},{"date":1713398400,"recommendations_up":0,"recommendations_down":1},{"date":1713484800,"recommendations_up":0,"recommendations_down":0},{"date":1713571200,"recommendations_up":0,"recommendations_down":0},{"date":1713657600,"recommendations_up":0,"recommendations_down":0},{"date":1713744000,"recommendations_up":0,"recommendations_down":0},{"date":1713830400,"recommendations_up":0,"recommendations_down":0},{"date":1713916800,"recommendations_up":0,"recommendations_down":0},{"date":1714003200,"recommendations_up":0,"recommendations_down":0},{"date":1714089600,"recommendations_up":0,"recommendations_down":1},{"date":1714176000,"recommendations_up":0,"recommendations_down":0},{"date":1714262400,"recommendations_up":0,"recommendations_down":0},{"date":1714348800,"recommendations_up":0,"recommendations_down":0},{"date":1714435200,"recommendations_up":0,"recommendations_down":0},{"date":1714521600,"recommendations_up":0,"recommendations_down":0},{"date":1714608000,"recommendations_up":0,"recommendations_down":0},{"date":1714694400,"recommendations_up":0,"recommendations_down":0},{"date":1714780800,"recommendations_up":0,"recommendations_down":0},{"date":1714867200,"recommendations_up":0,"recommendations_down":1},{"date":1714953600,"recommendations_up":0,"recommendations_down":0},{"date":1715040000,"recommendations_up":0,"recommendations_down":0},{"date":1715126400,"recommendations_up":1,"recommendations_down":0},{"date":1715212800,"recommendations_up":0,"recommendations_down":0},{"date":1715299200,"recommendations_up":0,"recommendations_down":1},{"date":1715385600,"recommendations_up":0,"recommendations_down":0},{"date":1715472000,"recommendations_up":0,"recommendations_down":1}]},"count_all_reviews":true,"expand_graph":false}